LICENSE
elz_py_tools/datastore/__init__.py
elz_py_tools/datastore/datastore.py
elz_py_tools/datastore/keys.py
elz_py_tools/datastore/model.py
elz_py_tools/drivers/__init__.py
elz_py_tools/drivers/amqp/__init__.py
elz_py_tools/drivers/amqp/client.py
elz_py_tools/drivers/graph/__init__.py
elz_py_tools/drivers/graph/parser.py
elz_py_tools/drivers/graph/publisher.py
elz_py_tools/drivers/graph/sparql.py
elz_py_tools/drivers/index/__init__.py
elz_py_tools/drivers/mongo/__init__.py
elz_py_tools/drivers/toolkit/__init__.py
elz_py_tools/drivers/toolkit/publisher.py
elz_py_tools/tasks/__init__.py
elz_py_tools/utilities/__init__.py
elz_py_tools/utilities/generator.py
elz_py_tools/utilities/helpers.py
elz_py_tools-0.1.4.dist-info/LICENSE
elz_py_tools-0.1.4.dist-info/WHEEL
elz_py_tools-0.1.4.dist-info/METADATA
elz_py_tools-0.1.4.dist-info/RECORD
