Metadata-Version: 2.1
Name: elz-py-tools
Version: 0.1.4
Summary: Python components compliant with Synaptix framework
Home-page: https://gitlab.com/elzeard/elz-py-tools
License: Apache-2.0
Author: Hervé
Author-email: herve.descombe@elzeard.co
Requires-Python: >=3.8,<4.0
Classifier: Environment :: Console
Classifier: License :: OSI Approved :: Apache Software License
Classifier: Operating System :: OS Independent
Classifier: Programming Language :: Python :: 3
Classifier: Programming Language :: Python :: 3.8
Classifier: Programming Language :: Python :: 3.9
Classifier: Topic :: Software Development :: Libraries :: Python Modules
Requires-Dist: aio-pika (>=6.8.0,<7.0.0)
Requires-Dist: elasticsearch (>=7.13.3,<8.0.0)
Requires-Dist: pymongo (>=3.11.4,<4.0.0)
Project-URL: Repository, https://gitlab.com/elzeard/elz-py-tools
